[
    {
        "timestamp": "2025-11-13T18:16:03.726759",
        "voltage": 226.7,
        "daily_energy": 557.8,
        "power": 557.8,
        "solar": 20.2,
        "power_factor": 6.7
    },
    {
        "timestamp": "2025-11-13T18:18:03.808806",
        "voltage": 232.0,
        "daily_energy": 499.3,
        "power": 499.3,
        "solar": 20.2,
        "power_factor": 6.7
    },
    {
        "timestamp": "2025-11-13T18:20:03.753806",
        "voltage": 232.8,
        "daily_energy": 506.7,
        "power": 506.7,
        "solar": 20.2,
        "power_factor": 6.6
    },
    {
        "timestamp": "2025-11-13T18:22:03.561295",
        "voltage": 232.9,
        "daily_energy": 496.3,
        "power": 496.3,
        "solar": 20.2,
        "power_factor": 6.6
    },
    {
        "timestamp": "2025-11-13T18:24:04.232337",
        "voltage": 234.6,
        "daily_energy": 492.7,
        "power": 492.7,
        "solar": 20.2,
        "power_factor": 6.6
    },
    {
        "timestamp": "2025-11-13T18:26:03.441845",
        "voltage": 231.3,
        "daily_energy": 493.7,
        "power": 493.7,
        "solar": 20.2,
        "power_factor": 6.5
    },
    {
        "timestamp": "2025-11-13T18:28:04.324789",
        "voltage": 231.8,
        "daily_energy": 533.7,
        "power": 533.7,
        "solar": 20.2,
        "power_factor": 6.6
    },
    {
        "timestamp": "2025-11-13T18:30:04.240170",
        "voltage": 233.8,
        "daily_energy": 535.3,
        "power": 535.3,
        "solar": 20.2,
        "power_factor": 6.6
    },
    {
        "timestamp": "2025-11-13T18:32:03.545598",
        "voltage": 234.9,
        "daily_energy": 548.0,
        "power": 548.0,
        "solar": 20.2,
        "power_factor": 6.5
    },
    {
        "timestamp": "2025-11-13T18:34:03.735283",
        "voltage": 234.7,
        "daily_energy": 546.6,
        "power": 546.6,
        "solar": 20.2,
        "power_factor": 7.0
    },
    {
        "timestamp": "2025-11-13T18:36:03.918153",
        "voltage": 230.5,
        "daily_energy": 577.0,
        "power": 577.0,
        "solar": 20.2,
        "power_factor": 7.0
    },
    {
        "timestamp": "2025-11-13T18:38:03.552963",
        "voltage": 228.6,
        "daily_energy": 544.0,
        "power": 544.0,
        "solar": 20.2,
        "power_factor": 7.0
    },
    {
        "timestamp": "2025-11-13T18:40:04.220506",
        "voltage": 229.2,
        "daily_energy": 542.7,
        "power": 542.7,
        "solar": 20.2,
        "power_factor": 7.1
    },
    {
        "timestamp": "2025-11-13T18:42:04.124062",
        "voltage": 232.3,
        "daily_energy": 549.5,
        "power": 549.5,
        "solar": 20.2,
        "power_factor": 7.1
    },
    {
        "timestamp": "2025-11-13T18:44:03.769777",
        "voltage": 231.0,
        "daily_energy": 546.0,
        "power": 546.0,
        "solar": 20.2,
        "power_factor": 6.6
    },
    {
        "timestamp": "2025-11-13T18:46:03.860629",
        "voltage": 231.8,
        "daily_energy": 544.1,
        "power": 544.1,
        "solar": 20.2,
        "power_factor": 6.6
    },
    {
        "timestamp": "2025-11-13T18:48:04.242304",
        "voltage": 234.0,
        "daily_energy": 567.1,
        "power": 567.1,
        "solar": 20.2,
        "power_factor": 6.7
    },
    {
        "timestamp": "2025-11-13T18:50:04.408379",
        "voltage": 235.0,
        "daily_energy": 539.0,
        "power": 539.0,
        "solar": 20.2,
        "power_factor": 6.8
    },
    {
        "timestamp": "2025-11-13T18:52:03.660174",
        "voltage": 233.9,
        "daily_energy": 538.9,
        "power": 538.9,
        "solar": 20.2,
        "power_factor": 6.8
    },
    {
        "timestamp": "2025-11-13T18:54:03.858807",
        "voltage": 234.7,
        "daily_energy": 536.5,
        "power": 536.5,
        "solar": 20.2,
        "power_factor": 6.7
    },
    {
        "timestamp": "2025-11-13T18:56:04.422188",
        "voltage": 232.5,
        "daily_energy": 518.7,
        "power": 518.7,
        "solar": 20.2,
        "power_factor": 6.5
    },
    {
        "timestamp": "2025-11-13T18:58:03.963456",
        "voltage": 233.6,
        "daily_energy": 542.2,
        "power": 542.2,
        "solar": 20.2,
        "power_factor": 6.5
    },
    {
        "timestamp": "2025-11-13T19:00:03.769062",
        "voltage": 234.0,
        "daily_energy": 477.1,
        "power": 477.1,
        "solar": 20.2,
        "power_factor": 6.4
    },
    {
        "timestamp": "2025-11-13T19:02:04.112585",
        "voltage": 234.1,
        "daily_energy": 525.6,
        "power": 525.6,
        "solar": 20.2,
        "power_factor": 6.6
    },
    {
        "timestamp": "2025-11-13T19:04:04.120027",
        "voltage": 233.6,
        "daily_energy": 480.9,
        "power": 480.9,
        "solar": 20.2,
        "power_factor": 6.6
    },
    {
        "timestamp": "2025-11-13T19:06:03.865115",
        "voltage": 234.9,
        "daily_energy": 521.6,
        "power": 521.6,
        "solar": 20.2,
        "power_factor": 6.5
    },
    {
        "timestamp": "2025-11-13T19:08:03.810288",
        "voltage": 234.6,
        "daily_energy": 496.3,
        "power": 496.3,
        "solar": 20.2,
        "power_factor": 6.6
    },
    {
        "timestamp": "2025-11-13T19:10:03.471405",
        "voltage": 235.9,
        "daily_energy": 505.3,
        "power": 505.3,
        "solar": 20.2,
        "power_factor": 6.6
    },
    {
        "timestamp": "2025-11-13T19:12:04.321000",
        "voltage": 235.9,
        "daily_energy": 501.9,
        "power": 501.9,
        "solar": 20.2,
        "power_factor": 6.5
    },
    {
        "timestamp": "2025-11-13T19:14:03.687664",
        "voltage": 236.7,
        "daily_energy": 500.8,
        "power": 500.8,
        "solar": 20.2,
        "power_factor": 6.5
    },
    {
        "timestamp": "2025-11-13T19:16:04.305982",
        "voltage": 234.6,
        "daily_energy": 498.7,
        "power": 498.7,
        "solar": 20.2,
        "power_factor": 6.8
    },
    {
        "timestamp": "2025-11-13T19:18:03.428085",
        "voltage": 236.4,
        "daily_energy": 508.5,
        "power": 508.5,
        "solar": 20.2,
        "power_factor": 7.0
    },
    {
        "timestamp": "2025-11-13T19:20:03.607390",
        "voltage": 234.9,
        "daily_energy": 546.5,
        "power": 546.5,
        "solar": 20.2,
        "power_factor": 7.1
    },
    {
        "timestamp": "2025-11-13T19:22:03.969103",
        "voltage": 234.4,
        "daily_energy": 542.2,
        "power": 542.2,
        "solar": 20.2,
        "power_factor": 7.0
    },
    {
        "timestamp": "2025-11-13T19:24:04.101391",
        "voltage": 235.1,
        "daily_energy": 551.0,
        "power": 551.0,
        "solar": 20.2,
        "power_factor": 7.0
    },
    {
        "timestamp": "2025-11-13T19:26:04.342123",
        "voltage": 235.0,
        "daily_energy": 542.4,
        "power": 542.4,
        "solar": 20.2,
        "power_factor": 6.4
    },
    {
        "timestamp": "2025-11-13T19:28:04.297703",
        "voltage": 235.2,
        "daily_energy": 533.0,
        "power": 533.0,
        "solar": 20.2,
        "power_factor": 6.6
    },
    {
        "timestamp": "2025-11-13T19:30:04.310947",
        "voltage": 235.1,
        "daily_energy": 560.9,
        "power": 560.9,
        "solar": 20.2,
        "power_factor": 6.6
    },
    {
        "timestamp": "2025-11-13T19:32:04.242107",
        "voltage": 232.0,
        "daily_energy": 550.8,
        "power": 550.8,
        "solar": 20.2,
        "power_factor": 6.6
    },
    {
        "timestamp": "2025-11-13T19:34:03.961580",
        "voltage": 236.6,
        "daily_energy": 539.8,
        "power": 539.8,
        "solar": 20.2,
        "power_factor": 6.6
    },
    {
        "timestamp": "2025-11-13T19:36:03.785227",
        "voltage": 235.5,
        "daily_energy": 608.6,
        "power": 608.6,
        "solar": 20.2,
        "power_factor": 6.5
    },
    {
        "timestamp": "2025-11-13T19:38:03.884681",
        "voltage": 233.3,
        "daily_energy": 651.8,
        "power": 651.8,
        "solar": 20.2,
        "power_factor": 6.5
    },
    {
        "timestamp": "2025-11-13T19:40:04.120903",
        "voltage": 235.5,
        "daily_energy": 576.9,
        "power": 576.9,
        "solar": 20.2,
        "power_factor": 6.4
    },
    {
        "timestamp": "2025-11-13T19:42:03.588509",
        "voltage": 238.2,
        "daily_energy": 581.4,
        "power": 581.4,
        "solar": 20.2,
        "power_factor": 6.5
    },
    {
        "timestamp": "2025-11-13T19:44:04.341290",
        "voltage": 232.5,
        "daily_energy": 568.8,
        "power": 568.8,
        "solar": 20.2,
        "power_factor": 6.4
    },
    {
        "timestamp": "2025-11-13T19:46:04.363118",
        "voltage": 237.3,
        "daily_energy": 583.8,
        "power": 583.8,
        "solar": 20.2,
        "power_factor": 6.4
    },
    {
        "timestamp": "2025-11-13T19:48:04.273752",
        "voltage": 239.5,
        "daily_energy": 547.8,
        "power": 547.8,
        "solar": 20.2,
        "power_factor": 6.2
    },
    {
        "timestamp": "2025-11-13T19:50:04.395606",
        "voltage": 239.7,
        "daily_energy": 542.8,
        "power": 542.8,
        "solar": 20.2,
        "power_factor": 6.2
    },
    {
        "timestamp": "2025-11-13T19:52:03.464046",
        "voltage": 240.1,
        "daily_energy": 557.5,
        "power": 557.5,
        "solar": 20.2,
        "power_factor": 6.3
    },
    {
        "timestamp": "2025-11-13T19:54:03.670580",
        "voltage": 236.5,
        "daily_energy": 546.8,
        "power": 546.8,
        "solar": 20.2,
        "power_factor": 6.3
    },
    {
        "timestamp": "2025-11-13T19:56:03.718813",
        "voltage": 237.5,
        "daily_energy": 536.8,
        "power": 536.8,
        "solar": 20.2,
        "power_factor": 6.7
    },
    {
        "timestamp": "2025-11-13T19:58:03.971076",
        "voltage": 237.9,
        "daily_energy": 536.5,
        "power": 536.5,
        "solar": 20.2,
        "power_factor": 6.7
    },
    {
        "timestamp": "2025-11-13T20:00:04.384749",
        "voltage": 237.7,
        "daily_energy": 530.5,
        "power": 530.5,
        "solar": 20.2,
        "power_factor": 6.7
    },
    {
        "timestamp": "2025-11-13T20:02:03.581575",
        "voltage": 238.7,
        "daily_energy": 522.2,
        "power": 522.2,
        "solar": 20.2,
        "power_factor": 6.7
    },
    {
        "timestamp": "2025-11-13T20:04:03.438526",
        "voltage": 237.5,
        "daily_energy": 540.5,
        "power": 540.5,
        "solar": 20.2,
        "power_factor": 6.6
    },
    {
        "timestamp": "2025-11-13T20:06:03.538754",
        "voltage": 238.4,
        "daily_energy": 551.4,
        "power": 551.4,
        "solar": 20.2,
        "power_factor": 6.1
    },
    {
        "timestamp": "2025-11-13T20:08:04.269392",
        "voltage": 239.5,
        "daily_energy": 502.6,
        "power": 502.6,
        "solar": 20.2,
        "power_factor": 6.2
    },
    {
        "timestamp": "2025-11-13T20:10:03.799039",
        "voltage": 241.0,
        "daily_energy": 515.6,
        "power": 515.6,
        "solar": 20.2,
        "power_factor": 6.2
    },
    {
        "timestamp": "2025-11-13T20:12:04.253983",
        "voltage": 241.3,
        "daily_energy": 517.6,
        "power": 517.6,
        "solar": 20.2,
        "power_factor": 6.2
    },
    {
        "timestamp": "2025-11-13T20:14:03.496134",
        "voltage": 240.7,
        "daily_energy": 498.5,
        "power": 498.5,
        "solar": 20.2,
        "power_factor": 6.3
    },
    {
        "timestamp": "2025-11-13T20:16:03.818277",
        "voltage": 239.4,
        "daily_energy": 492.3,
        "power": 492.3,
        "solar": 20.2,
        "power_factor": 6.3
    },
    {
        "timestamp": "2025-11-13T20:18:03.813114",
        "voltage": 239.7,
        "daily_energy": 495.0,
        "power": 495.0,
        "solar": 20.2,
        "power_factor": 6.2
    },
    {
        "timestamp": "2025-11-13T20:20:03.981293",
        "voltage": 239.2,
        "daily_energy": 536.1,
        "power": 536.1,
        "solar": 20.2,
        "power_factor": 6.3
    },
    {
        "timestamp": "2025-11-13T20:22:03.742466",
        "voltage": 239.8,
        "daily_energy": 492.4,
        "power": 492.4,
        "solar": 20.2,
        "power_factor": 6.4
    },
    {
        "timestamp": "2025-11-13T20:24:04.075482",
        "voltage": 236.4,
        "daily_energy": 490.3,
        "power": 490.3,
        "solar": 20.2,
        "power_factor": 6.3
    },
    {
        "timestamp": "2025-11-13T20:26:03.756836",
        "voltage": 240.8,
        "daily_energy": 527.9,
        "power": 527.9,
        "solar": 20.2,
        "power_factor": 6.4
    },
    {
        "timestamp": "2025-11-13T20:28:04.041529",
        "voltage": 239.3,
        "daily_energy": 572.2,
        "power": 572.2,
        "solar": 20.2,
        "power_factor": 6.4
    },
    {
        "timestamp": "2025-11-13T20:30:04.083535",
        "voltage": 240.3,
        "daily_energy": 567.2,
        "power": 567.2,
        "solar": 20.2,
        "power_factor": 6.3
    },
    {
        "timestamp": "2025-11-13T20:32:04.266525",
        "voltage": 239.5,
        "daily_energy": 554.3,
        "power": 554.3,
        "solar": 20.2,
        "power_factor": 6.3
    },
    {
        "timestamp": "2025-11-13T20:34:03.510170",
        "voltage": 240.7,
        "daily_energy": 616.7,
        "power": 616.7,
        "solar": 20.2,
        "power_factor": 6.3
    },
    {
        "timestamp": "2025-11-13T20:36:04.203808",
        "voltage": 242.1,
        "daily_energy": 550.5,
        "power": 550.5,
        "solar": 20.2,
        "power_factor": 6.8
    },
    {
        "timestamp": "2025-11-13T20:38:03.870931",
        "voltage": 239.9,
        "daily_energy": 564.5,
        "power": 564.5,
        "solar": 20.2,
        "power_factor": 6.8
    },
    {
        "timestamp": "2025-11-13T20:40:03.460717",
        "voltage": 241.3,
        "daily_energy": 544.5,
        "power": 544.5,
        "solar": 20.2,
        "power_factor": 6.9
    },
    {
        "timestamp": "2025-11-13T20:42:03.694963",
        "voltage": 240.9,
        "daily_energy": 538.3,
        "power": 538.3,
        "solar": 20.2,
        "power_factor": 6.9
    },
    {
        "timestamp": "2025-11-13T20:44:03.617287",
        "voltage": 239.4,
        "daily_energy": 540.0,
        "power": 540.0,
        "solar": 20.2,
        "power_factor": 6.9
    },
    {
        "timestamp": "2025-11-13T20:46:03.700734",
        "voltage": 240.1,
        "daily_energy": 566.9,
        "power": 566.9,
        "solar": 20.2,
        "power_factor": 6.3
    },
    {
        "timestamp": "2025-11-13T20:48:04.097723",
        "voltage": 239.1,
        "daily_energy": 526.1,
        "power": 526.1,
        "solar": 20.2,
        "power_factor": 6.4
    },
    {
        "timestamp": "2025-11-13T20:50:04.379195",
        "voltage": 240.1,
        "daily_energy": 537.5,
        "power": 537.5,
        "solar": 20.2,
        "power_factor": 6.3
    },
    {
        "timestamp": "2025-11-13T20:52:03.850301",
        "voltage": 240.0,
        "daily_energy": 534.0,
        "power": 534.0,
        "solar": 20.2,
        "power_factor": 6.3
    },
    {
        "timestamp": "2025-11-13T20:54:03.744469",
        "voltage": 238.3,
        "daily_energy": 545.4,
        "power": 545.4,
        "solar": 20.2,
        "power_factor": 6.3
    },
    {
        "timestamp": "2025-11-13T20:56:03.996743",
        "voltage": 238.5,
        "daily_energy": 543.8,
        "power": 543.8,
        "solar": 20.2,
        "power_factor": 6.3
    },
    {
        "timestamp": "2025-11-13T20:58:04.060893",
        "voltage": 239.5,
        "daily_energy": 537.7,
        "power": 537.7,
        "solar": 20.2,
        "power_factor": 6.4
    },
    {
        "timestamp": "2025-11-13T21:00:08.607819",
        "voltage": 237.9,
        "daily_energy": 521.7,
        "power": 521.7,
        "solar": 20.2,
        "power_factor": 6.3
    },
    {
        "timestamp": "2025-11-13T21:00:09.065594",
        "voltage": 237.9,
        "daily_energy": 521.7,
        "power": 521.7,
        "solar": 20.2,
        "power_factor": 6.3
    },
    {
        "timestamp": "2025-11-13T21:02:06.375626",
        "voltage": 236.1,
        "daily_energy": 535.3,
        "power": 535.3,
        "solar": 20.2,
        "power_factor": 6.4
    },
    {
        "timestamp": "2025-11-13T21:02:07.014342",
        "voltage": 236.1,
        "daily_energy": 535.3,
        "power": 535.3,
        "solar": 20.2,
        "power_factor": 6.4
    },
    {
        "timestamp": "2025-11-13T21:04:05.724433",
        "voltage": 232.1,
        "daily_energy": 523.3,
        "power": 523.3,
        "solar": 20.2,
        "power_factor": 6.4
    },
    {
        "timestamp": "2025-11-13T21:04:06.361720",
        "voltage": 232.1,
        "daily_energy": 523.3,
        "power": 523.3,
        "solar": 20.2,
        "power_factor": 6.4
    },
    {
        "timestamp": "2025-11-13T21:06:06.102196",
        "voltage": 226.9,
        "daily_energy": 508.2,
        "power": 508.2,
        "solar": 20.2,
        "power_factor": 6.4
    },
    {
        "timestamp": "2025-11-13T21:06:06.718428",
        "voltage": 226.9,
        "daily_energy": 508.2,
        "power": 508.2,
        "solar": 20.2,
        "power_factor": 6.4
    },
    {
        "timestamp": "2025-11-13T21:08:05.318595",
        "voltage": 226.9,
        "daily_energy": 517.8,
        "power": 517.8,
        "solar": 20.2,
        "power_factor": 6.5
    },
    {
        "timestamp": "2025-11-13T21:08:06.355488",
        "voltage": 226.9,
        "daily_energy": 517.8,
        "power": 517.8,
        "solar": 20.2,
        "power_factor": 6.5
    },
    {
        "timestamp": "2025-11-13T21:10:06.385225",
        "voltage": 224.0,
        "daily_energy": 508.4,
        "power": 508.4,
        "solar": 20.2,
        "power_factor": 6.4
    },
    {
        "timestamp": "2025-11-13T21:10:06.988388",
        "voltage": 224.0,
        "daily_energy": 508.4,
        "power": 508.4,
        "solar": 20.2,
        "power_factor": 6.4
    },
    {
        "timestamp": "2025-11-13T21:12:05.735759",
        "voltage": 233.7,
        "daily_energy": 533.1,
        "power": 533.1,
        "solar": 20.2,
        "power_factor": 6.4
    },
    {
        "timestamp": "2025-11-13T21:12:06.335519",
        "voltage": 233.7,
        "daily_energy": 533.1,
        "power": 533.1,
        "solar": 20.2,
        "power_factor": 6.4
    },
    {
        "timestamp": "2025-11-13T21:14:06.108089",
        "voltage": 235.0,
        "daily_energy": 549.3,
        "power": 549.3,
        "solar": 20.2,
        "power_factor": 6.8
    },
    {
        "timestamp": "2025-11-13T21:14:06.688813",
        "voltage": 235.0,
        "daily_energy": 549.3,
        "power": 549.3,
        "solar": 20.2,
        "power_factor": 6.8
    },
    {
        "timestamp": "2025-11-13T21:16:05.301998",
        "voltage": 234.7,
        "daily_energy": 496.5,
        "power": 496.5,
        "solar": 20.2,
        "power_factor": 6.8
    },
    {
        "timestamp": "2025-11-13T21:16:06.353685",
        "voltage": 235.3,
        "daily_energy": 496.5,
        "power": 496.5,
        "solar": 20.2,
        "power_factor": 6.8
    },
    {
        "timestamp": "2025-11-13T21:18:06.385165",
        "voltage": 236.3,
        "daily_energy": 493.6,
        "power": 493.6,
        "solar": 20.2,
        "power_factor": 6.9
    },
    {
        "timestamp": "2025-11-13T21:18:06.969082",
        "voltage": 236.3,
        "daily_energy": 493.6,
        "power": 493.6,
        "solar": 20.2,
        "power_factor": 6.9
    },
    {
        "timestamp": "2025-11-13T21:20:05.772290",
        "voltage": 234.2,
        "daily_energy": 500.3,
        "power": 500.3,
        "solar": 20.2,
        "power_factor": 6.8
    },
    {
        "timestamp": "2025-11-13T21:20:06.325152",
        "voltage": 234.2,
        "daily_energy": 500.3,
        "power": 500.3,
        "solar": 20.2,
        "power_factor": 6.8
    },
    {
        "timestamp": "2025-11-13T21:22:06.159021",
        "voltage": 235.1,
        "daily_energy": 488.2,
        "power": 488.2,
        "solar": 20.2,
        "power_factor": 6.8
    },
    {
        "timestamp": "2025-11-13T21:22:06.712377",
        "voltage": 235.1,
        "daily_energy": 488.2,
        "power": 488.2,
        "solar": 20.2,
        "power_factor": 6.8
    },
    {
        "timestamp": "2025-11-13T21:24:05.311567",
        "voltage": 236.9,
        "daily_energy": 497.1,
        "power": 497.1,
        "solar": 20.2,
        "power_factor": 6.2
    },
    {
        "timestamp": "2025-11-13T21:24:06.386344",
        "voltage": 236.5,
        "daily_energy": 488.2,
        "power": 488.2,
        "solar": 20.2,
        "power_factor": 6.3
    },
    {
        "timestamp": "2025-11-13T21:26:06.458304",
        "voltage": 237.3,
        "daily_energy": 490.5,
        "power": 490.5,
        "solar": 20.2,
        "power_factor": 6.4
    },
    {
        "timestamp": "2025-11-13T21:26:06.974457",
        "voltage": 237.3,
        "daily_energy": 490.5,
        "power": 490.5,
        "solar": 20.2,
        "power_factor": 6.4
    },
    {
        "timestamp": "2025-11-13T21:28:05.865597",
        "voltage": 236.6,
        "daily_energy": 508.3,
        "power": 508.3,
        "solar": 20.2,
        "power_factor": 6.3
    },
    {
        "timestamp": "2025-11-13T21:28:06.373551",
        "voltage": 236.6,
        "daily_energy": 508.3,
        "power": 508.3,
        "solar": 20.2,
        "power_factor": 6.3
    },
    {
        "timestamp": "2025-11-13T21:30:06.288818",
        "voltage": 240.3,
        "daily_energy": 490.1,
        "power": 490.1,
        "solar": 20.2,
        "power_factor": 6.4
    },
    {
        "timestamp": "2025-11-13T21:30:06.781930",
        "voltage": 240.3,
        "daily_energy": 490.1,
        "power": 490.1,
        "solar": 20.2,
        "power_factor": 6.4
    },
    {
        "timestamp": "2025-11-13T21:32:05.411125",
        "voltage": 240.3,
        "daily_energy": 528.0,
        "power": 528.0,
        "solar": 20.2,
        "power_factor": 6.4
    },
    {
        "timestamp": "2025-11-13T21:32:06.489997",
        "voltage": 239.3,
        "daily_energy": 529.7,
        "power": 529.7,
        "solar": 20.2,
        "power_factor": 6.4
    },
    {
        "timestamp": "2025-11-13T21:34:05.281670",
        "voltage": 233.4,
        "daily_energy": 479.8,
        "power": 479.8,
        "solar": 20.2,
        "power_factor": 6.4
    },
    {
        "timestamp": "2025-11-13T21:34:06.372247",
        "voltage": 233.8,
        "daily_energy": 474.6,
        "power": 474.6,
        "solar": 20.2,
        "power_factor": 6.4
    },
    {
        "timestamp": "2025-11-13T21:36:06.455116",
        "voltage": 234.9,
        "daily_energy": 484.6,
        "power": 484.6,
        "solar": 20.2,
        "power_factor": 6.3
    },
    {
        "timestamp": "2025-11-13T21:36:06.951157",
        "voltage": 234.9,
        "daily_energy": 484.6,
        "power": 484.6,
        "solar": 20.2,
        "power_factor": 6.3
    },
    {
        "timestamp": "2025-11-13T21:38:05.871776",
        "voltage": 238.3,
        "daily_energy": 442.2,
        "power": 442.2,
        "solar": 20.2,
        "power_factor": 6.3
    },
    {
        "timestamp": "2025-11-13T21:38:06.358958",
        "voltage": 238.9,
        "daily_energy": 446.0,
        "power": 446.0,
        "solar": 20.2,
        "power_factor": 6.3
    },
    {
        "timestamp": "2025-11-13T21:40:06.338171",
        "voltage": 239.4,
        "daily_energy": 441.4,
        "power": 441.4,
        "solar": 20.2,
        "power_factor": 6.2
    },
    {
        "timestamp": "2025-11-13T21:40:06.795396",
        "voltage": 239.4,
        "daily_energy": 441.4,
        "power": 441.4,
        "solar": 20.2,
        "power_factor": 6.2
    },
    {
        "timestamp": "2025-11-13T21:42:05.411758",
        "voltage": 236.7,
        "daily_energy": 1068.0,
        "power": 1068.0,
        "solar": 20.2,
        "power_factor": 6.1
    },
    {
        "timestamp": "2025-11-13T21:42:06.535633",
        "voltage": 236.2,
        "daily_energy": 1104.7,
        "power": 1104.7,
        "solar": 20.2,
        "power_factor": 6.1
    },
    {
        "timestamp": "2025-11-13T21:44:05.225107",
        "voltage": 236.3,
        "daily_energy": 1088.6,
        "power": 1088.6,
        "solar": 20.2,
        "power_factor": 6.2
    },
    {
        "timestamp": "2025-11-13T21:44:06.360751",
        "voltage": 236.9,
        "daily_energy": 1102.7,
        "power": 1102.7,
        "solar": 20.2,
        "power_factor": 6.2
    },
    {
        "timestamp": "2025-11-13T21:46:06.522173",
        "voltage": 236.1,
        "daily_energy": 1157.4,
        "power": 1157.4,
        "solar": 20.2,
        "power_factor": 6.1
    },
    {
        "timestamp": "2025-11-13T21:46:06.897985",
        "voltage": 236.1,
        "daily_energy": 1157.4,
        "power": 1157.4,
        "solar": 20.2,
        "power_factor": 6.1
    },
    {
        "timestamp": "2025-11-13T21:48:05.995446",
        "voltage": 236.7,
        "daily_energy": 1169.0,
        "power": 1169.0,
        "solar": 20.2,
        "power_factor": 6.2
    },
    {
        "timestamp": "2025-11-13T21:48:06.394745",
        "voltage": 235.8,
        "daily_energy": 1162.3,
        "power": 1162.3,
        "solar": 20.2,
        "power_factor": 6.2
    },
    {
        "timestamp": "2025-11-13T21:50:06.435480",
        "voltage": 237.8,
        "daily_energy": 916.3,
        "power": 916.3,
        "solar": 20.2,
        "power_factor": 6.3
    },
    {
        "timestamp": "2025-11-13T21:50:06.847400",
        "voltage": 237.8,
        "daily_energy": 916.3,
        "power": 916.3,
        "solar": 20.2,
        "power_factor": 6.3
    },
    {
        "timestamp": "2025-11-13T21:52:05.922049",
        "voltage": 233.2,
        "daily_energy": 502.3,
        "power": 502.3,
        "solar": 20.2,
        "power_factor": 6.2
    },
    {
        "timestamp": "2025-11-13T21:52:06.305067",
        "voltage": 233.0,
        "daily_energy": 505.4,
        "power": 505.4,
        "solar": 20.2,
        "power_factor": 6.2
    },
    {
        "timestamp": "2025-11-13T21:54:06.415007",
        "voltage": 232.4,
        "daily_energy": 499.1,
        "power": 499.1,
        "solar": 20.2,
        "power_factor": 6.8
    },
    {
        "timestamp": "2025-11-13T21:54:06.761900",
        "voltage": 232.4,
        "daily_energy": 499.1,
        "power": 499.1,
        "solar": 20.2,
        "power_factor": 6.8
    },
    {
        "timestamp": "2025-11-13T21:56:05.930760",
        "voltage": 240.2,
        "daily_energy": 537.9,
        "power": 537.9,
        "solar": 20.2,
        "power_factor": 6.8
    },
    {
        "timestamp": "2025-11-13T21:56:06.278307",
        "voltage": 240.2,
        "daily_energy": 537.9,
        "power": 537.9,
        "solar": 20.2,
        "power_factor": 6.8
    },
    {
        "timestamp": "2025-11-13T21:58:06.435318",
        "voltage": 233.2,
        "daily_energy": 489.7,
        "power": 489.7,
        "solar": 20.2,
        "power_factor": 6.7
    },
    {
        "timestamp": "2025-11-13T21:58:06.752165",
        "voltage": 233.2,
        "daily_energy": 489.7,
        "power": 489.7,
        "solar": 20.2,
        "power_factor": 6.7
    },
    {
        "timestamp": "2025-11-13T22:00:10.969056",
        "voltage": 241.7,
        "daily_energy": 500.3,
        "power": 500.3,
        "solar": 20.2,
        "power_factor": 6.7
    },
    {
        "timestamp": "2025-11-13T22:00:11.164781",
        "voltage": 241.7,
        "daily_energy": 500.3,
        "power": 500.3,
        "solar": 20.2,
        "power_factor": 6.7
    }
]